yica_yirage-1.1.0.dist-info/licenses/LICENSE
yirage/__init__.py
yirage/analysis.py
yirage/api.py
yirage/api_compat.py
yirage/export.py
yirage/profiler.py
yirage/version.py
yirage/visualize.py
yirage/yica_distributed_unified.py
yirage/compiler/__init__.py
yirage/compiler/auto_compiler.py
yirage/compiler/operator_registry.py
yirage/core/__init__.py
yirage/core/cim_ops.py
yirage/core/core.py
yirage/core/decorators.py
yirage/core/global_config.py
yirage/core/kernel.py
yirage/core/optimizer.py
yirage/core/threadblock.py
yirage/profiling/__init__.py
yirage/profiling/profiler.py
yirage/profiling/triton_profiler.py
yirage/profiling/yica_performance_monitor.py
yirage/profiling/yica_performance_tuner.py
yirage/utils/__init__.py
yirage/utils/graph_dataset.py
yirage/utils/utils.py
yirage/utils/visualizer.py
yirage/utils/warning_manager.py
yirage/yica/__init__.py
yirage/yica/yica_advanced.py
yirage/yica/yica_backend_integration.py
yirage/yica/yica_distributed.py
yirage/yica/yica_pytorch_backend.py
yica_yirage-1.1.0.dist-info/METADATA
yica_yirage-1.1.0.dist-info/WHEEL
yica_yirage-1.1.0.dist-info/entry_points.txt
yica_yirage-1.1.0.dist-info/top_level.txt
yica_yirage-1.1.0.dist-info/RECORD
