Metadata-Version: 2.4
Name: yica-yirage
Version: 1.1.0
Summary: YICA-Yirage: AI Computing Optimization Framework for In-Memory Computing Architecture
Author-email: YICA Team <contact@yica.ai>
Maintainer-email: YICA Team <contact@yica.ai>
License-Expression: MIT
Project-URL: Homepage, https://github.com/yica-ai/yica-yirage
Project-URL: Documentation, https://yica-yirage.readthedocs.io/
Project-URL: Repository, https://github.com/yica-ai/yica-yirage.git
Project-URL: Bug Tracker, https://github.com/yica-ai/yica-yirage/issues
Project-URL: Changelog, https://github.com/yica-ai/yica-yirage/blob/main/CHANGELOG.md
Keywords: ai,optimization,compiler,triton,yica,yirage,deep-learning,in-memory-computing
Classifier: Development Status :: 4 - Beta
Classifier: Intended Audience :: Developers
Classifier: Intended Audience :: Science/Research
Classifier: Operating System :: POSIX :: Linux
Classifier: Operating System :: MacOS :: MacOS X
Classifier: Operating System :: Microsoft :: Windows
Classifier: Programming Language :: Python :: 3
Classifier: Programming Language :: Python :: 3.8
Classifier: Programming Language :: Python :: 3.9
Classifier: Programming Language :: Python :: 3.10
Classifier: Programming Language :: Python :: 3.11
Classifier: Programming Language :: Python :: 3.12
Classifier: Programming Language :: C++
Classifier: Topic :: Scientific/Engineering :: Artificial Intelligence
Classifier: Topic :: Software Development :: Compilers
Classifier: Topic :: System :: Hardware
Requires-Python: >=3.8
License-File: LICENSE
Requires-Dist: numpy>=1.19.0
Requires-Dist: torch>=2.5.1
Requires-Dist: z3-solver>=4.8.0
Provides-Extra: dev
Requires-Dist: pytest>=6.0; extra == "dev"
Requires-Dist: pytest-cov>=3.0; extra == "dev"
Requires-Dist: black>=21.0; extra == "dev"
Requires-Dist: flake8>=3.8; extra == "dev"
Requires-Dist: mypy>=0.900; extra == "dev"
Requires-Dist: sphinx>=4.0; extra == "dev"
Requires-Dist: sphinx-rtd-theme>=1.0; extra == "dev"
Requires-Dist: pre-commit>=2.15; extra == "dev"
Provides-Extra: cuda
Requires-Dist: cupy>=9.0.0; extra == "cuda"
Requires-Dist: nvidia-ml-py>=11.0.0; extra == "cuda"
Provides-Extra: rocm
Requires-Dist: torch-rocm>=1.12.0; extra == "rocm"
Provides-Extra: torch-cim
Requires-Dist: torch_cim; extra == "torch-cim"
Provides-Extra: triton
Requires-Dist: triton>=2.0.0; sys_platform == "linux" and extra == "triton"
Provides-Extra: all
Requires-Dist: yica-yirage[cuda,dev,torch_cim]; extra == "all"
Dynamic: license-file
